quickcodec/__init__.pxd
quickcodec/__init__.py
quickcodec/__main__.py
quickcodec/_core.cpython-310-i386-linux-gnu.so
quickcodec/_core.pyi
quickcodec/about.py
quickcodec/bitstream.cpython-310-i386-linux-gnu.so
quickcodec/bitstream.pxd
quickcodec/bitstream.pyi
quickcodec/buffer.cpython-310-i386-linux-gnu.so
quickcodec/buffer.pxd
quickcodec/buffer.pyi
quickcodec/bytesource.cpython-310-i386-linux-gnu.so
quickcodec/bytesource.pxd
quickcodec/datasets.py
quickcodec/descriptor.cpython-310-i386-linux-gnu.so
quickcodec/descriptor.pxd
quickcodec/descriptor.pyi
quickcodec/dictionary.cpython-310-i386-linux-gnu.so
quickcodec/dictionary.pxd
quickcodec/dictionary.pyi
quickcodec/error.cpython-310-i386-linux-gnu.so
quickcodec/error.pxd
quickcodec/error.pyi
quickcodec/format.cpython-310-i386-linux-gnu.so
quickcodec/format.pxd
quickcodec/format.pyi
quickcodec/frame.cpython-310-i386-linux-gnu.so
quickcodec/frame.pxd
quickcodec/frame.pyi
quickcodec/logging.cpython-310-i386-linux-gnu.so
quickcodec/logging.pxd
quickcodec/logging.pyi
quickcodec/opaque.cpython-310-i386-linux-gnu.so
quickcodec/opaque.pxd
quickcodec/option.cpython-310-i386-linux-gnu.so
quickcodec/option.pxd
quickcodec/option.pyi
quickcodec/packet.cpython-310-i386-linux-gnu.so
quickcodec/packet.pxd
quickcodec/packet.py
quickcodec/packet.pyi
quickcodec/plane.cpython-310-i386-linux-gnu.so
quickcodec/plane.pxd
quickcodec/plane.pyi
quickcodec/py.typed
quickcodec/stream.cpython-310-i386-linux-gnu.so
quickcodec/stream.pxd
quickcodec/stream.pyi
quickcodec/utils.cpython-310-i386-linux-gnu.so
quickcodec/utils.pxd
quickcodec/vfast.cpython-310-i386-linux-gnu.so
quickcodec/vfast.py
quickcodec/attachments/__init__.py
quickcodec/attachments/stream.cpython-310-i386-linux-gnu.so
quickcodec/attachments/stream.pxd
quickcodec/attachments/stream.pyi
quickcodec/audio/__init__.pxd
quickcodec/audio/__init__.py
quickcodec/audio/__init__.pyi
quickcodec-0.0.1.dist-info/METADATA
quickcodec-0.0.1.dist-info/WHEEL
quickcodec-0.0.1.dist-info/entry_points.txt
quickcodec-0.0.1.dist-info/top_level.txt
quickcodec-0.0.1.dist-info/RECORD
quickcodec-0.0.1.dist-info/licenses/LICENSE.txt
